bagofholding/__init__.py
bagofholding/_version.py
bagofholding/bag.py
bagofholding/content.py
bagofholding/exceptions.py
bagofholding/metadata.py
bagofholding/trie.py
bagofholding/widget.py
bagofholding/h5/__init__.py
bagofholding/h5/bag.py
bagofholding/h5/content.py
bagofholding/h5/context.py
bagofholding/h5/dtypes.py
bagofholding/h5/triebag.py
bagofholding-0.1.5.dist-info/METADATA
bagofholding-0.1.5.dist-info/WHEEL
bagofholding-0.1.5.dist-info/licenses/LICENSE
bagofholding-0.1.5.dist-info/RECORD
