Metadata-Version: 2.4
Name: bagofholding
Version: 0.1.5
Summary: bagofholding - browsable, partially-reloadable serialization for pickleable python objects.
Project-URL: Homepage, https://pyiron.org/
Project-URL: Documentation, https://bagofholding.readthedocs.io
Project-URL: Repository, https://github.com/pyiron/bagofholding
Author-email: Liam Huber <liamhuber@greyhavensolutions.com>
License: BSD 3-Clause License
License-File: LICENSE
Keywords: pyiron
Classifier: Development Status :: 4 - Beta
Classifier: Intended Audience :: Science/Research
Classifier: License :: OSI Approved :: BSD License
Classifier: Operating System :: OS Independent
Classifier: Programming Language :: Python :: 3.11
Classifier: Programming Language :: Python :: 3.12
Classifier: Programming Language :: Python :: 3.13
Classifier: Programming Language :: Python :: 3.14
Classifier: Topic :: Scientific/Engineering
Requires-Python: <3.15,>=3.11
Requires-Dist: bidict==0.23.1
Requires-Dist: h5py<3.15.0,>=3.12.1
Requires-Dist: numpy<2.4.0,>=1.26.4
Requires-Dist: pygtrie<2.6.0,>=2.5.0
Requires-Dist: pyiron-snippets<2.0.0,>=1.0.0
Provides-Extra: widget
Requires-Dist: ipytree==0.2.2; extra == 'widget'
Requires-Dist: traitlets==5.14.3; extra == 'widget'
